animecli
