Metadata-Version: 2.1
Name: animecli
Version: 1.0.1
Summary: animecli is a tool to retrieve all information about your favourite anime in the comfort of your terminal, using the jikan.moe API.
Home-page: https://github.com/ryanvij/animecli
Author: ryanvij
Author-email: ryan.vijay2006@gmail.com
License: MIT
Platform: UNKNOWN
License-File: LICENSE
